picsellia_tf1/__init__.py
picsellia_tf1/pxl_tf.py
picsellia_tf1/pxl_utils.py
picsellia_tf1/object_detection/__init__.py
picsellia_tf1/object_detection/eval_util.py
picsellia_tf1/object_detection/eval_util_test.py
picsellia_tf1/object_detection/export_inference_graph.py
picsellia_tf1/object_detection/export_tflite_graph_lib_tf2.py
picsellia_tf1/object_detection/export_tflite_graph_lib_tf2_test.py
picsellia_tf1/object_detection/export_tflite_graph_tf2.py
picsellia_tf1/object_detection/export_tflite_ssd_graph.py
picsellia_tf1/object_detection/export_tflite_ssd_graph_lib.py
picsellia_tf1/object_detection/export_tflite_ssd_graph_lib_tf1_test.py
picsellia_tf1/object_detection/exporter.py
picsellia_tf1/object_detection/exporter_lib_tf2_test.py
picsellia_tf1/object_detection/exporter_lib_v2.py
picsellia_tf1/object_detection/exporter_main_v2.py
picsellia_tf1/object_detection/exporter_tf1_test.py
picsellia_tf1/object_detection/inputs.py
picsellia_tf1/object_detection/inputs_test.py
picsellia_tf1/object_detection/model_hparams.py
picsellia_tf1/object_detection/model_lib.py
picsellia_tf1/object_detection/model_lib_tf1_test.py
picsellia_tf1/object_detection/model_lib_tf2_test.py
picsellia_tf1/object_detection/model_lib_v2.py
picsellia_tf1/object_detection/model_main.py
picsellia_tf1/object_detection/model_main_tf2.py
picsellia_tf1/object_detection/model_tpu_main.py
picsellia_tf1/object_detection/anchor_generators/__init__.py
picsellia_tf1/object_detection/anchor_generators/flexible_grid_anchor_generator.py
picsellia_tf1/object_detection/anchor_generators/flexible_grid_anchor_generator_test.py
picsellia_tf1/object_detection/anchor_generators/grid_anchor_generator.py
picsellia_tf1/object_detection/anchor_generators/grid_anchor_generator_test.py
picsellia_tf1/object_detection/anchor_generators/multiple_grid_anchor_generator.py
picsellia_tf1/object_detection/anchor_generators/multiple_grid_anchor_generator_test.py
picsellia_tf1-0.6.dist-info/METADATA
picsellia_tf1-0.6.dist-info/WHEEL
picsellia_tf1-0.6.dist-info/top_level.txt
picsellia_tf1-0.6.dist-info/RECORD
