Metadata-Version: 2.1
Name: picsellia-tf1
Version: 0.6
Summary: Tensorflow Object Detection Library with TF1.0
Home-page: UNKNOWN
License: UNKNOWN
Platform: UNKNOWN
Requires-Python: >3.6
Requires-Dist: tensorflow (==1.15.0)
Requires-Dist: pillow
Requires-Dist: lxml
Requires-Dist: matplotlib
Requires-Dist: Cython
Requires-Dist: contextlib2
Requires-Dist: tf-slim
Requires-Dist: six
Requires-Dist: pycocotools
Requires-Dist: lvis
Requires-Dist: scipy
Requires-Dist: pandas
